frazzl/__init__.py
frazzl/__main__.py
frazzl/constants.py
frazzl/gateway/index.js
frazzl/gateway/package.json
frazzl/services/__init__.py
frazzl/types/__init__.py
frazzl/types/directive.py
frazzl/types/entity.py
frazzl/types/gateway.py
frazzl/types/objects.py
frazzl/types/scalars.py
frazzl/types/service.py
frazzl/types/service_manager.py
frazzl-0.0.1a1.dist-info/LICENSE
frazzl-0.0.1a1.dist-info/METADATA
frazzl-0.0.1a1.dist-info/WHEEL
frazzl-0.0.1a1.dist-info/entry_points.txt
frazzl-0.0.1a1.dist-info/top_level.txt
frazzl-0.0.1a1.dist-info/RECORD
