Metadata-Version: 2.1
Name: frazzl
Version: 0.0.1a1
Summary: UNKNOWN
Home-page: UNKNOWN
Author: jimtheplant
Author-email: jimtheplant1@gmail.com
License: UNKNOWN
Platform: UNKNOWN
Requires-Python: >=3.7
Requires-Dist: ariadne (==0.7)
Requires-Dist: uvicorn (==0.10.8)
Requires-Dist: nodeenv (==1.3.3)
Requires-Dist: click (==7.0)
